{"latest_csv_date": "2017-06-02 02:06:32", "feature_flags": ["influenceexplorer"], "terms": [{"end_year": 2012, "start_year": 2011, "name": "2011-2012", "sessions": ["2011-2012"]}, {"end_year": 2014, "start_year": 2013, "name": "2013-2014", "sessions": ["2013-2014"]}, {"end_year": 2016, "start_year": 2015, "name": "2015-2016", "sessions": ["2015-2016"]}, {"end_year": 2018, "start_year": 2017, "name": "2017-2018", "sessions": ["2017-2018"]}], "name": "Kansas", "latest_csv_url": "http://s.openstates.org/downloads/2017-06-02-ks-csv.zip", "legislature_name": "Kansas State Legislature", "id": "ks", "abbreviation": "ks", "latest_update": "2018-02-12 09:21:35", "latest_json_url": "http://s.openstates.org/downloads/2017-06-30-ks-json.zip", "chambers": {"upper": {"name": "Senate", "title": "Senator"}, "lower": {"name": "House", "title": "Representative"}}, "session_details": {"2015-2016": {"type": "primary", "display_name": "2015-2016 Regular Session", "start_date": "2013-01-14 00:00:00"}, "2013-2014": {"type": "primary", "display_name": "2013-2014 Regular Session", "start_date": "2013-01-14 00:00:00"}, "2017-2018": {"type": "primary", "display_name": "2017-2018 Regular Session", "start_date": "2017-01-09 00:00:00", "end_date": "2017-05-19 00:00:00"}, "2011-2012": {"type": "primary", "display_name": "2011-2012 Regular Session", "start_date": "2011-01-12 00:00:00"}}, "capitol_timezone": "America/Chicago", "latest_json_date": "2017-06-30 10:35:22", "legislature_url": "http://www.kslegislature.org/"}